Metadata-Version: 1.1
Name: django-commandlog
Version: 0.1.10
Summary: A Django app to log management commands
Home-page: https://github.com/achedeuzot/django-commandlog
Author: Klemen Sever
Author-email: klemen@achedeuzot.me
License: BSD License
Download-URL: https://github.com/achedeuzot/django-commandlog/tarball/0.1.10
Platform: UNKNOWN
Classifier: Development Status :: 5 - Production/Stable
Classifier: Environment :: Web Environment
Classifier: Framework :: Django
Classifier: Intended Audience :: Developers
Classifier: License :: OSI Approved :: BSD License
Classifier: Operating System :: OS Independent
Classifier: Programming Language :: Python
Classifier: Programming Language :: Python :: 2.7
Classifier: Programming Language :: Python :: 3
Classifier: Topic :: Internet :: WWW/HTTP
Classifier: Topic :: Internet :: WWW/HTTP :: Dynamic Content
